pyutl/__init__.py
pyutl/localenv.py
pyutl/oracle.py
pyutl/remote.py
pyutl/sendmail.py
pyutl-2.9.dist-info/LICENSE.txt
pyutl-2.9.dist-info/METADATA
pyutl-2.9.dist-info/WHEEL
pyutl-2.9.dist-info/top_level.txt
pyutl-2.9.dist-info/RECORD
