Metadata-Version: 2.1
Name: pyutl
Version: 2.9
Summary: functions and utilities to recycle code
Home-page: https://github.com/Jesrat/pyutl.git
Author: Josue Gomez <jgomez@jesrat.com>
Author-email: jgomez@cloudsyss.com
License: UNKNOWN
Platform: UNKNOWN
Classifier: Programming Language :: Python :: 3
Classifier: License :: OSI Approved :: MIT License
Classifier: Operating System :: OS Independent
License-File: LICENSE.txt
